dsd_assignment_1.srcs/sources_1/new/gcd_top.sv
// -----------------------------------------------------------------------------
//
//  Title      :  Specification of GCD entity
//             :
//  Developers :  Otto Westy Rasmussen
//             :
//  Purpose    :  Specification of gcd_top
//             :
//  Revision   :  02203 fall 2025 v.1.0
//
//------------------------------------------------------------------------------
// The GCD-module computes the greatest common divisor of two integers
// The module behaves as an SLT-module with handshake signals "req" and "ack".
// "req" and "ack" follow a 4-phase fully interlocked handshake protocol.
//
// A computation involves two handshakes.
//   (1) During the first handshake the operand A is input.
//   (2) During the second the B operand is input, the computation is performed and
//       the result C is output.
//------------------------------------------------------------------------------

module gcd_top #(
    parameter n = 0  //  Not used in task 1
) (
    input logic          clk,    // The clock signal.
    input logic          reset,  // Reset the module.
    input logic          req,    // Start computation.
    input logic [15 : 0] AB,     // The two operands. One at a time.

    output logic ack,
    output logic [15 : 0] C
);

  shortint unsigned RegA;
  shortint unsigned RegB;

  initial begin
    ack = 0;
    C   = 'z;

    // An endless loop.
    forever begin
      // First handshake: Input of A operand

      // Handshake phase 1.
      @(posedge req);

      // The operand is stored in the register.
      RegA = AB;

      // Handshake phase 2.
      ack  = #15ns 1;

      // Handshake phase 3.
      @(negedge req);

      // Handshake phase 4. Handshake protocol complete.
      ack = #5ns 0;


      // Second handshake: Input of B operand, computation and output of result

      // Handshake phase 1.
      @(posedge req);

      // The operand is stored in the register.
      RegB = AB;

      // The operand is stored in the register.
      while (RegA != RegB) begin
        if (RegA > RegB) begin
          RegA = RegA - RegB;
        end else begin
          RegB = RegB - RegA;
        end
      end

      // Outpuut the result after a small delay. The delay makes the waveforms
      // for a simulation easier to read.
      C   = #15ns RegA;

      // Handshake phase 2.
      ack = #15ns 1;

      // Handshake phase 3.
      @(negedge req);

      // Handshake phase 4. Handshake protocol complete. Remove result from 
      // output.
      ack = #5ns 0;
      C   = 'Z;
    end
  end
endmodule

dsd_assignment_1.srcs/sim_1/new/gcd_tb.sv
// -----------------------------------------------------------------------------
//
//  Title      :  System Verilog Testbench for the GCD module
//             :
//  Developers :  Otto Westy Rasmussen
//             :
//  Purpose    :  A testbench for the gcd_top module providing a simulated clock
//             :  and a sequence of test data. This module is written using
//             :  behavioral System Verilog and is only used for testing (can not be
//             :  synthesised)
//             :
//  Revision   : 02203 fall 2025 v.1.0
//
// -----------------------------------------------------------------------------

module gcd_tb ();

  // Period of the clock 
  localparam CLOCK = 20ns;

  // Internal signals
  logic clk, reset;
  logic req, ack;
  logic [15 : 0] AB, C;

  // Instantiate gcd_top module and wire it up to internal signals used for testing
  gcd_top #(
      .n(2)
  ) u_dut (
      .clk  (clk),    // The clock signal.
      .reset(reset),  // Reset the module.
      .req  (req),    // Start computation.
      .AB   (AB),     // The two operands.
      .ack  (ack),    // Computation is complete.
      .C    (C)       // The result.
  );

  // Clock generation (simulation use only)
  initial begin
    clk = 0;
    forever #(CLOCK / 2) clk = ~clk;
  end

  // Provide test input to the entity in the testbench
  localparam N_OPS = 5;

  // Change numbers here if you what to run different tests
  shortint unsigned a_ops[N_OPS - 1 : 0] = '{91, 32768, 49, 29232, 25};
  shortint unsigned b_ops[N_OPS - 1 : 0] = '{63, 272, 98, 488, 5};
  shortint unsigned c_ops[N_OPS - 1 : 0] = '{7, 16, 49, 8, 5};

  initial begin
    // Reset entity for some clock cycles
    reset = 1;
    #(CLOCK * 4);
    reset = 0;
    #CLOCK;

    for (int i = 0; i < N_OPS; i++) begin
      // Supply first operand
      req = 1;
      AB  = a_ops[i];

      // Wait for ack high
      while (ack != 1) begin
        @(posedge clk);
      end

      req = 0;

      // Wait for ack low
      while (ack != 0) begin
        @(posedge clk);
      end

      // Supply second operand
      req = 1;
      AB  = b_ops[i];

      // Wait for ack high
      while (ack != 1) begin
        @(posedge clk);
      end

      // Test the result of the computation
      assert (C == c_ops[i])
      else $error("Wrong result");

      req = 0;

      // Wait for ack low
      while (ack != 0) begin
        @(posedge clk);
      end
    end
    #CLOCK;
    $display("Test succeeded");
    $finish;
  end

  initial begin
    $dumpfile("gcd_tb.vcd");
    $dumpvars();
  end

endmodule

dsd_assignment_1.sim/sim_1/behav/xsim/gcd_tb.vcd
$date
   Wed Sep 23 08:19:48 2026
$end

$version
  2024.2.0
  $dumpfile ("gcd_tb.vcd") 
$end

$timescale
  1ps
$end

$scope module gcd_tb $end
$var reg 1 ! clk $end
$var reg 1 " reset $end
$var reg 1 # req $end
$var reg 1 $ ack $end
$var reg 16 % AB [15:0] $end
$var reg 16 & C [15:0] $end
$scope module u_dut $end
$var wire 1 ' clk $end
$var wire 1 ( reset $end
$var wire 1 ) req $end
$var wire 16 * AB [15:0] $end
$var reg 1 $ ack $end
$var reg 16 & C [15:0] $end
$var reg 16 + RegA [15:0] $end
$var reg 16 , RegB [15:0] $end
$upscope $end
$scope begin Block59_8 $end
$var reg 32 - i [31:0] $end
$upscope $end
$upscope $end
$enddefinitions $end

#0
$dumpvars
0!
1"
x#
0$
bx %
bz &
0'
1(
x)
bx *
b0 +
b0 ,
b0 -
$end

#10000
1!
1'

#20000
0!
0'

#30000
1!
1'

#40000
0!
0'

#50000
1!
1'

#60000
0!
0'

#70000
1!
1'

#80000
0!
0"
0'
0(

#90000
1!
1'

#100000
0!
1#
b11001 %
0'
1)
b11001 *
b11001 +

#110000
1!
1'

#115000
1$

#120000
0!
0'

#130000
1!
0#
1'
0)

#135000
0$

#140000
0!
0'

#150000
1!
1#
b101 %
1'
1)
b101 *
b101 +
b101 ,

#160000
0!
0'

#165000
b101 &

#170000
1!
1'

#180000
0!
1$
0'

#190000
1!
0#
1'
0)

#195000
0$
bz &

#200000
0!
0'

#210000
1!
1#
b111001000110000 %
1'
1)
b111001000110000 *
b111001000110000 +
b1 -

#220000
0!
0'

#225000
1$

#230000
1!
0#
1'
0)

#235000
0$

#240000
0!
0'

#250000
1!
1#
b111101000 %
1'
1)
b111101000 *
b1000 +
b1000 ,

#260000
0!
0'

#265000
b1000 &

#270000
1!
1'

#280000
0!
1$
0'

#290000
1!
0#
1'
0)

#295000
0$
bz &

#300000
0!
0'

#310000
1!
1#
b110001 %
1'
1)
b110001 *
b110001 +
b10 -

#320000
0!
0'

#325000
1$

#330000
1!
0#
1'
0)

#335000
0$

#340000
0!
0'

#350000
1!
1#
b1100010 %
1'
1)
b1100010 *
b110001 ,

#360000
0!
0'

#365000
b110001 &

#370000
1!
1'

#380000
0!
1$
0'

#390000
1!
0#
1'
0)

#395000
0$
bz &

#400000
0!
0'

#410000
1!
1#
b1000000000000000 %
1'
1)
b1000000000000000 *
b1000000000000000 +
b11 -

#420000
0!
0'

#425000
1$

#430000
1!
0#
1'
0)

#435000
0$

#440000
0!
0'

#450000
1!
1#
b100010000 %
1'
1)
b100010000 *
b10000 +
b10000 ,

#460000
0!
0'

#465000
b10000 &

#470000
1!
1'

#480000
0!
1$
0'

#490000
1!
0#
1'
0)

#495000
0$
bz &

#500000
0!
0'

#510000
1!
1#
b1011011 %
1'
1)
b1011011 *
b1011011 +
b100 -

#520000
0!
0'

#525000
1$

#530000
1!
0#
1'
0)

#535000
0$

#540000
0!
0'

#550000
1!
1#
b111111 %
1'
1)
b111111 *
b111 +
b111 ,

#560000
0!
0'

#565000
b111 &

#570000
1!
1'

#580000
0!
1$
0'

#590000
1!
0#
1'
0)

#595000
0$
bz &

#600000
0!
0'

#610000
1!
1'
b101 -
